{"openapi":"3.0.3","info":{"title":"Casa do Código Service","description":"Casa do Código HTTP service","version":"1.0"},"servers":[{"url":"http://localhost:3333","description":"hosts for Casa do Código Service."}],"paths":{"/actors":{"post":{"tags":["catalog"],"summary":"create_actor catalog","operationId":"catalog#create_actor","requestBody":{"required":true,"content":{"application/json":{"schema":{"$ref":"#/components/schemas/CreateActorRequestBody"},"example":{"description":"te3","email":"hildegard_cruickshank@stroman.net","name":"Voluptates deleniti."}}}},"responses":{"201":{"description":"","content":{"application/json":{"schema":{"$ref":"#/components/schemas/ActorDTO"},"example":{"created_at":"Laborum dolore aperiam.","description":"u11","email":"braxton@ward.net","id":"Non voluptas similique sunt itaque et.","name":"Qui id cumque doloremque quod esse voluptates."}}}},"400":{"description":"","content":{"application/vnd.goa.error":{"schema":{"$ref":"#/components/schemas/Error"},"example":{"fault":true,"id":"123abc","message":"parameter 'p' must be an integer","name":"bad_request","temporary":true,"timeout":true}}}}}}},"/actors/{id}":{"get":{"tags":["catalog"],"summary":"show_actor catalog","operationId":"catalog#show_actor","parameters":[{"name":"id","in":"path","description":"ID","required":true,"schema":{"type":"string","description":"ID","example":"Nam quaerat itaque libero dolores officia minus."},"example":"Porro hic."}],"responses":{"200":{"description":"","content":{"application/json":{"schema":{"$ref":"#/components/schemas/ActorDTO"},"example":{"created_at":"Et ab.","description":"rci","email":"jake_orn@kohler.com","id":"Blanditiis ratione quas hic dolorem nemo nisi.","name":"Esse error."}}}},"404":{"description":"","content":{"application/vnd.goa.error":{"schema":{"$ref":"#/components/schemas/Error"},"example":{"fault":true,"id":"123abc","message":"parameter 'p' must be an integer","name":"bad_request","temporary":false,"timeout":false}}}}}}},"/books":{"get":{"tags":["catalog"],"summary":"list_books catalog","operationId":"catalog#list_books","responses":{"200":{"description":"","content":{"application/json":{"schema":{"type":"array","items":{"$ref":"#/components/schemas/BookDTO"},"example":[{"actor_ids":["Fugiat itaque cum dolor quisquam sint at.","Minima est et.","Ut quis aut iste qui.","Sunt eum quisquam sit recusandae laudantium iste."],"category_ids":["Autem harum facilis debitis velit velit mollitia.","Velit eligendi asperiores quibusdam dicta."],"id":"Commodi corporis excepturi expedita necessitatibus ab.","isbn":"Qui aspernatur velit nobis voluptatem.","issue":"Dolor officia.","pages":1436892520498150648,"price":20.232424,"summary":"Quod nisi.","synopsis":"nwu","title":"Ut porro quis explicabo sit error."},{"actor_ids":["Fugiat itaque cum dolor quisquam sint at.","Minima est et.","Ut quis aut iste qui.","Sunt eum quisquam sit recusandae laudantium iste."],"category_ids":["Autem harum facilis debitis velit velit mollitia.","Velit eligendi asperiores quibusdam dicta."],"id":"Commodi corporis excepturi expedita necessitatibus ab.","isbn":"Qui aspernatur velit nobis voluptatem.","issue":"Dolor officia.","pages":1436892520498150648,"price":20.232424,"summary":"Quod nisi.","synopsis":"nwu","title":"Ut porro quis explicabo sit error."},{"actor_ids":["Fugiat itaque cum dolor quisquam sint at.","Minima est et.","Ut quis aut iste qui.","Sunt eum quisquam sit recusandae laudantium iste."],"category_ids":["Autem harum facilis debitis velit velit mollitia.","Velit eligendi asperiores quibusdam dicta."],"id":"Commodi corporis excepturi expedita necessitatibus ab.","isbn":"Qui aspernatur velit nobis voluptatem.","issue":"Dolor officia.","pages":1436892520498150648,"price":20.232424,"summary":"Quod nisi.","synopsis":"nwu","title":"Ut porro quis explicabo sit error."}]},"example":[{"actor_ids":["Fugiat itaque cum dolor quisquam sint at.","Minima est et.","Ut quis aut iste qui.","Sunt eum quisquam sit recusandae laudantium iste."],"category_ids":["Autem harum facilis debitis velit velit mollitia.","Velit eligendi asperiores quibusdam dicta."],"id":"Commodi corporis excepturi expedita necessitatibus ab.","isbn":"Qui aspernatur velit nobis voluptatem.","issue":"Dolor officia.","pages":1436892520498150648,"price":20.232424,"summary":"Quod nisi.","synopsis":"nwu","title":"Ut porro quis explicabo sit error."},{"actor_ids":["Fugiat itaque cum dolor quisquam sint at.","Minima est et.","Ut quis aut iste qui.","Sunt eum quisquam sit recusandae laudantium iste."],"category_ids":["Autem harum facilis debitis velit velit mollitia.","Velit eligendi asperiores quibusdam dicta."],"id":"Commodi corporis excepturi expedita necessitatibus ab.","isbn":"Qui aspernatur velit nobis voluptatem.","issue":"Dolor officia.","pages":1436892520498150648,"price":20.232424,"summary":"Quod nisi.","synopsis":"nwu","title":"Ut porro quis explicabo sit error."}]}}}}},"post":{"tags":["catalog"],"summary":"create_book catalog","operationId":"catalog#create_book","requestBody":{"required":true,"content":{"application/json":{"schema":{"$ref":"#/components/schemas/CreateBookRequestBody"},"example":{"actor_ids":["Et necessitatibus impedit quam.","Commodi similique et.","Provident at hic quibusdam sint et.","Atque assumenda dolor quia et dolore unde."],"category_ids":["Sit sequi.","Sed sed dicta facere officia."],"isbn":"Accusantium a expedita illo.","issue":"Perferendis perspiciatis.","pages":3951472581591739083,"price":20.86182,"summary":"Est asperiores provident inventore.","synopsis":"n1z","title":"Provident ducimus."}}}},"responses":{"201":{"description":"","content":{"application/json":{"schema":{"$ref":"#/components/schemas/BookDTO"},"example":{"actor_ids":["Distinctio iusto corporis eum amet.","Tempora alias quis.","Qui fugit ut praesentium.","Hic est soluta."],"category_ids":["Aliquid ullam.","Minima cupiditate consectetur quidem mollitia ab.","Distinctio et quasi harum nam sit ut.","Perferendis adipisci excepturi qui qui repellat dolor."],"id":"Ipsum rerum quia ducimus voluptatum.","isbn":"Veritatis officiis.","issue":"Quibusdam aut eum libero dolor.","pages":7390490842971779351,"price":20.992483,"summary":"Dolorum in autem.","synopsis":"d7k","title":"Dignissimos et occaecati dolorem."}}}},"400":{"description":"","content":{"application/vnd.goa.error":{"schema":{"$ref":"#/components/schemas/Error"},"example":{"fault":true,"id":"123abc","message":"parameter 'p' must be an integer","name":"bad_request","temporary":true,"timeout":true}}}}}}},"/books/{id}":{"get":{"tags":["catalog"],"summary":"show_book catalog","operationId":"catalog#show_book","parameters":[{"name":"id","in":"path","description":"ID","required":true,"schema":{"type":"string","description":"ID","example":"Animi molestiae iure aut consectetur."},"example":"A blanditiis praesentium corporis et corporis cum."}],"responses":{"200":{"description":"","content":{"application/json":{"schema":{"$ref":"#/components/schemas/BookDTO"},"example":{"actor_ids":["Rem quasi voluptatum ut.","Officia eum veritatis nam est qui.","Rerum commodi.","Sed voluptate voluptatem veniam laudantium."],"category_ids":["Eum consequatur rem sunt voluptates sed amet.","Labore possimus asperiores.","Ea officiis voluptatem est.","Deserunt accusantium non fuga reprehenderit."],"id":"Ab perferendis voluptatibus error ullam natus.","isbn":"Vel ipsa unde delectus esse.","issue":"Asperiores et.","pages":999998687732247347,"price":20.422737,"summary":"In nam quo cupiditate minus tempore.","synopsis":"34i","title":"Molestiae ipsam totam quia quae aut hic."}}}},"404":{"description":"","content":{"application/vnd.goa.error":{"schema":{"$ref":"#/components/schemas/Error"},"example":{"fault":false,"id":"123abc","message":"parameter 'p' must be an integer","name":"bad_request","temporary":true,"timeout":false}}}}}}},"/carts":{"post":{"tags":["catalog"],"summary":"create_cart catalog","operationId":"catalog#create_cart","requestBody":{"required":true,"content":{"application/json":{"schema":{"$ref":"#/components/schemas/CreateCartRequestBody"},"example":{"customer_id":"Voluptatem deserunt expedita minus quia nobis reprehenderit.","items":[{"amount":1131047539,"book_id":"Corporis maiores labore autem occaecati eligendi fugit."},{"amount":1131047539,"book_id":"Corporis maiores labore autem occaecati eligendi fugit."},{"amount":1131047539,"book_id":"Corporis maiores labore autem occaecati eligendi fugit."},{"amount":1131047539,"book_id":"Corporis maiores labore autem occaecati eligendi fugit."}],"total":0.4391943}}}},"responses":{"201":{"description":"","content":{"application/json":{"schema":{"$ref":"#/components/schemas/CartDTO"},"example":{"customer_id":"Omnis quo sint.","id":"Beatae exercitationem itaque necessitatibus voluptatem quae neque.","items":[{"amount":745111911,"book_id":"Quos aut aliquid."},{"amount":745111911,"book_id":"Quos aut aliquid."}],"total":0.32053176}}}},"400":{"description":"","content":{"application/vnd.goa.error":{"schema":{"$ref":"#/components/schemas/Error"},"example":{"fault":true,"id":"123abc","message":"parameter 'p' must be an integer","name":"bad_request","temporary":false,"timeout":false}}}}}}},"/categories":{"post":{"tags":["catalog"],"summary":"create_category catalog","operationId":"catalog#create_category","requestBody":{"required":true,"content":{"application/json":{"schema":{"$ref":"#/components/schemas/CreateCategoryRequestBody"},"example":{"name":"Quis est."}}}},"responses":{"201":{"description":"","content":{"application/json":{"schema":{"$ref":"#/components/schemas/CategoryDTO"},"example":{"id":"Tempore ut.","name":"Quibusdam non voluptatem quis iusto."}}}},"400":{"description":"","content":{"application/vnd.goa.error":{"schema":{"$ref":"#/components/schemas/Error"},"example":{"fault":true,"id":"123abc","message":"parameter 'p' must be an integer","name":"bad_request","temporary":false,"timeout":true}}}}}}},"/categories/{id}":{"get":{"tags":["catalog"],"summary":"show_category catalog","operationId":"catalog#show_category","parameters":[{"name":"id","in":"path","description":"ID","required":true,"schema":{"type":"string","description":"ID","example":"Officiis atque in ratione."},"example":"Consequatur aut itaque praesentium laborum molestias placeat."}],"responses":{"200":{"description":"","content":{"application/json":{"schema":{"$ref":"#/components/schemas/CategoryDTO"},"example":{"id":"Vel quo quo.","name":"Qui voluptatem dolorem ut omnis non."}}}},"404":{"description":"","content":{"application/vnd.goa.error":{"schema":{"$ref":"#/components/schemas/Error"},"example":{"fault":false,"id":"123abc","message":"parameter 'p' must be an integer","name":"bad_request","temporary":false,"timeout":true}}}}}}},"/countries":{"post":{"tags":["catalog"],"summary":"create_country catalog","operationId":"catalog#create_country","requestBody":{"required":true,"content":{"application/json":{"schema":{"$ref":"#/components/schemas/CreateCategoryRequestBody"},"example":{"name":"Ullam minus enim possimus eligendi."}}}},"responses":{"201":{"description":"","content":{"application/json":{"schema":{"$ref":"#/components/schemas/CountryDTO"},"example":{"id":"Recusandae sed harum voluptates quia non.","name":"Totam dolor.","state_ids":"Asperiores et inventore asperiores doloribus commodi."}}}},"400":{"description":"","content":{"application/vnd.goa.error":{"schema":{"$ref":"#/components/schemas/Error"},"example":{"fault":false,"id":"123abc","message":"parameter 'p' must be an integer","name":"bad_request","temporary":false,"timeout":false}}}}}}},"/customers":{"post":{"tags":["catalog"],"summary":"create_customer catalog","operationId":"catalog#create_customer","requestBody":{"required":true,"content":{"application/json":{"schema":{"$ref":"#/components/schemas/CreateCustomerRequestBody"},"example":{"address":{"address":"Recusandae occaecati animi.","cep":"Quis fugit corporis aliquid beatae sequi.","city":"Placeat sit et est atque.","complement":"Et vitae.","country_id":"Rem consectetur quo voluptate.","state_id":"Earum esse enim doloremque."},"cart_ids":["Ad sed incidunt similique.","Autem dolorem consequatur dicta commodi earum et.","Eaque doloribus rerum.","Nostrum veniam."],"document":"Nesciunt assumenda aperiam excepturi harum enim vero.","email":"orie@stark.name","first_name":"Delectus et et ea officiis.","last_name":"Voluptas dicta.","phone":"Placeat aut hic iure voluptatem."}}}},"responses":{"201":{"description":"","content":{"application/json":{"schema":{"$ref":"#/components/schemas/CustomerDTO"},"example":{"address":{"address":"Quisquam dolorem nobis totam.","cep":"Dolorem soluta fugiat deleniti nobis quam.","city":"Qui inventore eligendi tenetur dolores provident.","complement":"Autem accusantium.","country_id":"Eos quos.","state_id":"Expedita corrupti."},"cart_ids":["Error ea.","Minus omnis aspernatur dicta.","Qui et eius.","Quia deserunt expedita."],"document":"Nesciunt et.","email":"reva@gerlach.net","first_name":"Libero magnam.","id":"Qui eos vel quidem nostrum qui.","last_name":"Voluptate quis velit.","phone":"Mollitia rerum ullam."}}}},"400":{"description":"","content":{"application/vnd.goa.error":{"schema":{"$ref":"#/components/schemas/Error"},"example":{"fault":false,"id":"123abc","message":"parameter 'p' must be an integer","name":"bad_request","temporary":true,"timeout":true}}}}}}},"/states":{"post":{"tags":["catalog"],"summary":"create_state catalog","operationId":"catalog#create_state","requestBody":{"required":true,"content":{"application/json":{"schema":{"$ref":"#/components/schemas/CreateStateRequestBody"},"example":{"country_id":"Dolorum neque ut ex ex voluptas inventore.","name":"Eaque recusandae alias itaque ipsa et."}}}},"responses":{"201":{"description":"","content":{"application/json":{"schema":{"$ref":"#/components/schemas/StateDTO"},"example":{"country_id":"Corporis harum praesentium consequatur dolor quam.","id":"Facere veniam porro debitis.","name":"Sed eos iure dolor."}}}},"400":{"description":"","content":{"application/vnd.goa.error":{"schema":{"$ref":"#/components/schemas/Error"},"example":{"fault":false,"id":"123abc","message":"parameter 'p' must be an integer","name":"bad_request","temporary":true,"timeout":true}}}}}}},"/swagger.json":{"get":{"tags":["swagger"],"summary":"Download ../../gen/http/openapi.json","operationId":"swagger#/swagger.json","responses":{"200":{"description":"File downloaded"}}}}},"components":{"schemas":{"ActorDTO":{"type":"object","properties":{"created_at":{"type":"string","example":"Non aut."},"description":{"type":"string","example":"ph8","maxLength":400},"email":{"type":"string","example":"rachael@huelfranecki.name","format":"email"},"id":{"type":"string","example":"Molestias autem itaque quaerat illum."},"name":{"type":"string","example":"Atque repudiandae omnis doloremque."}},"example":{"created_at":"Eveniet nihil.","description":"qy4","email":"cody.mertz@reichert.net","id":"Autem recusandae qui ea est.","name":"Sed asperiores consectetur."},"required":["id","name","email","description","created_at"]},"AddressDTO":{"type":"object","properties":{"address":{"type":"string","example":"Aut nulla totam molestias."},"cep":{"type":"string","example":"Quo architecto ducimus quae veniam."},"city":{"type":"string","example":"Dicta earum corporis quam."},"complement":{"type":"string","example":"Quam repellat qui est."},"country_id":{"type":"string","example":"Dolorem consequatur et aut."},"state_id":{"type":"string","example":"Voluptatem ducimus quae aut voluptatem quidem."}},"description":"Address Type","example":{"address":"Et dignissimos.","cep":"Dolorem reprehenderit pariatur voluptatem eum.","city":"Iure nihil nostrum soluta.","complement":"Iusto labore voluptas laborum.","country_id":"Officia est.","state_id":"Optio consequatur."},"required":["address","complement","city","country_id","state_id","cep"]},"BookDTO":{"type":"object","properties":{"actor_ids":{"type":"array","items":{"type":"string","example":"Non molestiae nisi qui iste ut aut."},"example":["Non reiciendis aut et.","Sunt perspiciatis eos illum aut amet impedit."]},"category_ids":{"type":"array","items":{"type":"string","example":"Quasi voluptatem est blanditiis ad."},"example":["Atque ad eius nihil doloremque recusandae.","Nulla dolor inventore facilis quasi optio.","Aut qui.","Ut facere."]},"id":{"type":"string","example":"Nihil cum est debitis aut."},"isbn":{"type":"string","example":"Id nam."},"issue":{"type":"string","example":"Quia quis id consequatur repudiandae consequatur."},"pages":{"type":"integer","example":6082499958143793342,"minimum":100},"price":{"type":"number","example":20.681482,"minimum":20},"summary":{"type":"string","example":"Illum consectetur quasi."},"synopsis":{"type":"string","example":"yaj","maxLength":500},"title":{"type":"string","example":"Voluptate ex doloremque aut."}},"example":{"actor_ids":["Expedita consequatur beatae autem alias.","Ducimus et eveniet quae.","Eos dolorem ullam veniam.","Aut recusandae illo incidunt."],"category_ids":["Nesciunt eum.","Itaque mollitia porro impedit architecto natus est.","Minus debitis nihil labore optio.","Voluptatum nulla error natus ut minima."],"id":"Nostrum sed eius est velit.","isbn":"Tempora et.","issue":"Non voluptate eos aut.","pages":6941906146793493319,"price":20.862757,"summary":"Velit provident laboriosam dolore tempore qui.","synopsis":"3h0","title":"Inventore veniam amet ea eos porro."},"required":["id","title","synopsis","price","pages","isbn","issue","category_ids","actor_ids"]},"CartDTO":{"type":"object","properties":{"customer_id":{"type":"string","example":"Ut totam rerum perspiciatis."},"id":{"type":"string","example":"Cumque quo."},"items":{"type":"array","items":{"$ref":"#/components/schemas/ItemDTO"},"example":[{"amount":745111911,"book_id":"Quos aut aliquid."},{"amount":745111911,"book_id":"Quos aut aliquid."}]},"total":{"type":"number","example":0.3254637,"format":"float"}},"example":{"customer_id":"Et natus autem dolorem.","id":"Consequatur illum sint laborum adipisci.","items":[{"amount":745111911,"book_id":"Quos aut aliquid."},{"amount":745111911,"book_id":"Quos aut aliquid."},{"amount":745111911,"book_id":"Quos aut aliquid."}],"total":0.5460747},"required":["id","total","items","customer_id"]},"CategoryDTO":{"type":"object","properties":{"id":{"type":"string","example":"Rerum rerum."},"name":{"type":"string","example":"Eligendi corrupti nemo in eveniet."}},"example":{"id":"Molestiae ducimus in est amet rerum.","name":"Placeat iste fuga nobis ab facere."},"required":["id","name"]},"CountryDTO":{"type":"object","properties":{"id":{"type":"string","example":"Quis corrupti qui et ullam."},"name":{"type":"string","example":"Consequuntur excepturi nisi."},"state_ids":{"type":"string","example":"Aliquid molestiae et molestias necessitatibus."}},"example":{"id":"Quisquam quo ut perspiciatis incidunt sed.","name":"Dolor esse recusandae at mollitia blanditiis.","state_ids":"Et corporis consequatur cupiditate et."},"required":["id","name"]},"CreateActorRequestBody":{"type":"object","properties":{"description":{"type":"string","example":"bb1","maxLength":400},"email":{"type":"string","example":"carmine.borer@borer.biz","format":"email"},"name":{"type":"string","example":"Et laudantium quidem."}},"example":{"description":"chr","email":"modesto@auer.info","name":"Nam eaque perspiciatis possimus culpa."},"required":["name","email","description"]},"CreateBookRequestBody":{"type":"object","properties":{"actor_ids":{"type":"array","items":{"type":"string","example":"Autem et magnam consectetur aperiam fugit ut."},"example":["Odio sed et commodi sint perferendis ut.","Placeat perferendis ut ab quia et."]},"category_ids":{"type":"array","items":{"type":"string","example":"Sapiente repellat hic est et veniam nihil."},"example":["Quo et exercitationem est temporibus et non.","Nobis sapiente molestias eos aliquid velit ipsa.","Nostrum et est adipisci ut.","Quas ipsum sed."]},"isbn":{"type":"string","example":"Ex quam aut optio."},"issue":{"type":"string","example":"Illum ea quos."},"pages":{"type":"integer","example":6168420072366203472,"minimum":100},"price":{"type":"number","example":20.313433,"minimum":20},"summary":{"type":"string","example":"Officiis nam fuga."},"synopsis":{"type":"string","example":"tku","maxLength":500},"title":{"type":"string","example":"Non commodi mollitia accusamus."}},"example":{"actor_ids":["Est nemo sed praesentium velit.","Sed maxime reiciendis reprehenderit tempora.","Consequuntur quia quae ex veniam aut."],"category_ids":["Placeat iusto dolores.","Provident iure ab architecto quibusdam facere eum."],"isbn":"Velit dolore sunt earum.","issue":"Quia nam.","pages":3188178871419411856,"price":20.599123,"summary":"Quis in.","synopsis":"5pd","title":"Recusandae numquam laboriosam suscipit ea itaque sequi."},"required":["title","synopsis","price","pages","isbn","issue","category_ids","actor_ids"]},"CreateCartRequestBody":{"type":"object","properties":{"customer_id":{"type":"string","example":"Natus eligendi."},"items":{"type":"array","items":{"$ref":"#/components/schemas/ItemDTO"},"example":[{"amount":1131047539,"book_id":"Corporis maiores labore autem occaecati eligendi fugit."},{"amount":1131047539,"book_id":"Corporis maiores labore autem occaecati eligendi fugit."}]},"total":{"type":"number","example":0.19798604,"format":"float"}},"example":{"customer_id":"Ducimus perspiciatis.","items":[{"amount":1131047539,"book_id":"Corporis maiores labore autem occaecati eligendi fugit."},{"amount":1131047539,"book_id":"Corporis maiores labore autem occaecati eligendi fugit."},{"amount":1131047539,"book_id":"Corporis maiores labore autem occaecati eligendi fugit."}],"total":0.11667609},"required":["total","items","customer_id"]},"CreateCategoryRequestBody":{"type":"object","properties":{"name":{"type":"string","example":"Quasi doloremque voluptatem earum rerum."}},"example":{"name":"Tempore qui dolore architecto deserunt adipisci."},"required":["name"]},"CreateCustomerRequestBody":{"type":"object","properties":{"address":{"$ref":"#/components/schemas/AddressDTO"},"cart_ids":{"type":"array","items":{"type":"string","example":"Voluptates dicta nihil a."},"example":["Voluptate voluptatem sed nemo eius accusantium dolor.","Libero est et quidem totam."]},"document":{"type":"string","example":"Laborum non."},"email":{"type":"string","example":"isaias_bosco@block.biz","format":"email"},"first_name":{"type":"string","example":"Beatae et pariatur distinctio inventore qui libero."},"last_name":{"type":"string","example":"Alias ipsa."},"phone":{"type":"string","example":"Eius ab reiciendis atque et at."}},"example":{"address":{"address":"Recusandae occaecati animi.","cep":"Quis fugit corporis aliquid beatae sequi.","city":"Placeat sit et est atque.","complement":"Et vitae.","country_id":"Rem consectetur quo voluptate.","state_id":"Earum esse enim doloremque."},"cart_ids":["Vel at.","Aut ullam non.","Velit repudiandae nam maxime quia."],"document":"Est sunt qui ratione aperiam labore ad.","email":"vidal_bednar@tromp.info","first_name":"Iste nam ut provident magnam in.","last_name":"Voluptatem dolore qui recusandae veniam omnis quibusdam.","phone":"Aut voluptate quasi deleniti quia sit."},"required":["first_name","last_name","email","document","address","phone"]},"CreateStateRequestBody":{"type":"object","properties":{"country_id":{"type":"string","example":"Quam consequatur sint ratione quia quisquam."},"name":{"type":"string","example":"Provident veritatis dolorem necessitatibus praesentium deserunt."}},"example":{"country_id":"Impedit eveniet ut praesentium voluptatem ipsum.","name":"Ut cum ut."},"required":["name","country_id"]},"CustomerDTO":{"type":"object","properties":{"address":{"$ref":"#/components/schemas/AddressDTO"},"cart_ids":{"type":"array","items":{"type":"string","example":"Est iste quis."},"example":["Asperiores non labore sit.","Atque est ipsam impedit."]},"document":{"type":"string","example":"Sapiente sed repudiandae iure molestiae voluptatem."},"email":{"type":"string","example":"devon@emardgibson.com","format":"email"},"first_name":{"type":"string","example":"Quia eum quaerat est excepturi commodi officiis."},"id":{"type":"string","example":"Voluptas consectetur occaecati."},"last_name":{"type":"string","example":"Rerum in qui velit totam et."},"phone":{"type":"string","example":"Maiores est animi quibusdam."}},"example":{"address":{"address":"Quisquam dolorem nobis totam.","cep":"Dolorem soluta fugiat deleniti nobis quam.","city":"Qui inventore eligendi tenetur dolores provident.","complement":"Autem accusantium.","country_id":"Eos quos.","state_id":"Expedita corrupti."},"cart_ids":["Dolorum autem qui excepturi suscipit maxime illum.","Aut veritatis voluptatem.","Sunt enim consectetur at aut maiores qui."],"document":"Accusamus id.","email":"myrtie@kerluke.com","first_name":"Perspiciatis qui accusamus asperiores vitae et.","id":"Porro non excepturi assumenda et explicabo.","last_name":"Nobis numquam maxime vel non.","phone":"Eos maxime earum."},"required":["id","first_name","last_name","email","document","address","phone"]},"Error":{"type":"object","properties":{"fault":{"type":"boolean","description":"Is the error a server-side fault?","example":true},"id":{"type":"string","description":"ID is a unique identifier for this particular occurrence of the problem.","example":"123abc"},"message":{"type":"string","description":"Message is a human-readable explanation specific to this occurrence of the problem.","example":"parameter 'p' must be an integer"},"name":{"type":"string","description":"Name is the name of this class of errors.","example":"bad_request"},"temporary":{"type":"boolean","description":"Is the error temporary?","example":false},"timeout":{"type":"boolean","description":"Is the error a timeout?","example":true}},"example":{"fault":true,"id":"123abc","message":"parameter 'p' must be an integer","name":"bad_request","temporary":true,"timeout":false},"required":["name","id","message","temporary","timeout","fault"]},"ItemDTO":{"type":"object","properties":{"amount":{"type":"integer","example":2009770618,"format":"int32"},"book_id":{"type":"string","example":"Dolor omnis eum qui quidem."}},"description":"Item Type","example":{"amount":1432877830,"book_id":"Similique officia quibusdam vitae."},"required":["book_id","amount"]},"StateDTO":{"type":"object","properties":{"country_id":{"type":"string","example":"Dolore ut et atque error velit."},"id":{"type":"string","example":"Soluta quia voluptas debitis dolorem in."},"name":{"type":"string","example":"Autem commodi."}},"example":{"country_id":"Corrupti excepturi voluptas est ullam.","id":"Molestiae amet ut quos asperiores.","name":"Numquam eos."},"required":["id","name","country_id"]}}}}